mockdjangosaml2/__init__.py
mockdjangosaml2/settings.py
mockdjangosaml2/urls.py
mockdjangosaml2/views.py
mockdjangosaml2/static/mockdjangosaml2/aai_logo_localhost.png
mockdjangosaml2/static/mockdjangosaml2/login.css
mockdjangosaml2/templates/mockdjangosaml2/login.html
mockdjangosaml2-0.16.1.dist-info/DESCRIPTION.rst
mockdjangosaml2-0.16.1.dist-info/METADATA
mockdjangosaml2-0.16.1.dist-info/RECORD
mockdjangosaml2-0.16.1.dist-info/WHEEL
mockdjangosaml2-0.16.1.dist-info/metadata.json
mockdjangosaml2-0.16.1.dist-info/top_level.txt
