Metadata-Version: 2.0
Name: mockdjangosaml2
Version: 0.16.1
Summary: Django application that mocks functionality of djangosaml2 app for testing and development purposes.
Home-page: http://github.com/darbula/mockdjangosaml2
Author: Damir Arbula
Author-email: damir.arbula@gmail.com
License: BSD
Platform: Windows
Platform: Linux
Platform: Mac OSX
Classifier: Development Status :: 5 - Production/Stable
Classifier: Environment :: Web Environment
Classifier: Framework :: Django
Classifier: Intended Audience :: Developers
Classifier: License :: OSI Approved :: BSD License
Classifier: Operating System :: OS Independent
Classifier: Programming Language :: Python
Classifier: Topic :: Security
Requires-Dist: Django (>=1.4)
